{
  "ci": {
    "collect": {
      "numberOfRuns": 1,
      "url": [
        "https://markhazleton.com/",
        "https://markhazleton.com/articles.html",
        "https://markhazleton.com/web-project-mechanics.html"
      ]
    },
    "assert": {
      "assertions": {
        "categories:performance": ["warn", {"minScore": 0.8}],
        "categories:accessibility": ["warn", {"minScore": 0.8}],
        "categories:seo": ["warn", {"minScore": 0.8}]
      }
    },
    "upload": {
      "target": "filesystem",
      "outputDir": "lhci"
    }
  }
}
